starrocks_br/__init__.py
starrocks_br/cli.py
starrocks_br/concurrency.py
starrocks_br/config.py
starrocks_br/db.py
starrocks_br/error_handler.py
starrocks_br/exceptions.py
starrocks_br/executor.py
starrocks_br/health.py
starrocks_br/history.py
starrocks_br/labels.py
starrocks_br/logger.py
starrocks_br/planner.py
starrocks_br/repository.py
starrocks_br/restore.py
starrocks_br/schema.py
starrocks_br/timezone.py
starrocks_br/utils.py
starrocks_br-0.5.2.dist-info/licenses/LICENSE
starrocks_br-0.5.2.dist-info/METADATA
starrocks_br-0.5.2.dist-info/WHEEL
starrocks_br-0.5.2.dist-info/entry_points.txt
starrocks_br-0.5.2.dist-info/top_level.txt
starrocks_br-0.5.2.dist-info/RECORD
