Metadata-Version: 2.4
Name: starrocks-br
Version: 0.5.2
Summary: StarRocks Backup and Restore automation tool
Requires-Python: >=3.10
License-File: LICENSE
Requires-Dist: click<9,>=8.1.7
Requires-Dist: PyYAML<7,>=6.0.1
Requires-Dist: mysql-connector-python<10,>=9.0.0
Provides-Extra: dev
Requires-Dist: pytest<9,>=8.3.2; extra == "dev"
Requires-Dist: pytest-mock<4,>=3.14.0; extra == "dev"
Requires-Dist: pytest-cov<6,>=5.0.0; extra == "dev"
Requires-Dist: ruff<1,>=0.8.0; extra == "dev"
Requires-Dist: pre-commit<5,>=4.0.0; extra == "dev"
Dynamic: license-file
